{
    "status": "success",
    "message": "",
    "data": {
        "name": "Product 1",
        "rate": 10,
        "quantity": 10,
        "category_id": 1,
        "brand_id": 1,
        "description": "Qui aut quia soluta ut et repellendus aut.",
        "meta_title": "jqfpfenwpledzbrovcmnsylb",
        "meta_description": "sdovbzcbfmbwnxpgvrqzdi",
        "meta_keywords": "dvrisbpzc",
        "slug": "product-1",
        "updated_at": "2023-05-18T00:00:00.000000Z",
        "created_at": "2023-05-18T00:00:00.000000Z",
        "id": 1
    }
}
